emulica-1.3.1.dist-info/METADATA
emulica-1.3.1.dist-info/WHEEL
emulica-1.3.1.dist-info/licenses/LICENSE
emulica/__init__.py
emulica/core/__init__.py
emulica/core/controler.py
emulica/core/emuML.py
emulica/core/emulation.py
emulica/core/plot.py
emulica/core/properties.py
emulica-1.3.1.dist-info/RECORD
