Metadata-Version: 2.1
Name: emulica
Version: 1.3.1
Summary: Emulation of logistic systems
Author-Email: Rémi Pannequin <remi.pannequin@univ-lorraine.fr>
License: GPL-3
Classifier: Intended Audience :: Education
Classifier: Intended Audience :: Manufacturing
Classifier: Intended Audience :: Science/Research
Classifier: License :: OSI Approved :: GNU General Public License v3 (GPLv3)
Classifier: Operating System :: OS Independent
Classifier: Programming Language :: Python :: 3
Project-URL: Homepage, https://github.com/remipannequin/emulica-core
Requires-Python: >=3.6
Requires-Dist: matplotlib
Requires-Dist: simpy>4.0.0
Requires-Dist: twisted
